dbeasyorm/__init__.py
dbeasyorm/__main__.py
dbeasyorm/config.py
dbeasyorm/commands/__init__.py
dbeasyorm/commands/abstraction.py
dbeasyorm/commands/command_manager.py
dbeasyorm/commands/update_db_command.py
dbeasyorm/db/__init__.py
dbeasyorm/db/backends/__init__.py
dbeasyorm/db/backends/abstract.py
dbeasyorm/db/backends/postgres.py
dbeasyorm/db/backends/sqlite.py
dbeasyorm/fields/__init__.py
dbeasyorm/fields/abstract.py
dbeasyorm/fields/boolean_field.py
dbeasyorm/fields/byte_field.py
dbeasyorm/fields/float_field.py
dbeasyorm/fields/foreign_key.py
dbeasyorm/fields/integer_filed.py
dbeasyorm/fields/text_field.py
dbeasyorm/migrations/__init__.py
dbeasyorm/migrations/messages.py
dbeasyorm/migrations/migration.py
dbeasyorm/migrations/migration_detecter.py
dbeasyorm/migrations/migration_executor.py
dbeasyorm/migrations/migration_handler.py
dbeasyorm/migrations/model_classes_loader.py
dbeasyorm/models/__init__.py
dbeasyorm/models/abstract.py
dbeasyorm/models/exeptions.py
dbeasyorm/models/model.py
dbeasyorm/query/__init__.py
dbeasyorm/query/abstract.py
dbeasyorm/query/exeptions.py
dbeasyorm/query/query_counter.py
dbeasyorm/query/query_creator.py
dbeasyorm/query/utils.py
tests/db_backends_tests/__init__.py
tests/db_backends_tests/sqlite_tests/__init__.py
tests/db_backends_tests/sqlite_tests/test_sqlite_connection.py
tests/db_backends_tests/sqlite_tests/test_sqlite_creating_delete_query.py
tests/db_backends_tests/sqlite_tests/test_sqlite_creating_insert_query.py
tests/db_backends_tests/sqlite_tests/test_sqlite_creating_select_query.py
tests/db_backends_tests/sqlite_tests/test_sqlite_creating_update_query.py
tests/db_backends_tests/sqlite_tests/test_sqlite_join_table_query.py
tests/db_backends_tests/sqlite_tests/test_table_migration.py
tests/fields_tests/__init__.py
tests/fields_tests/test_boolean_field.py
tests/fields_tests/test_byte_field.py
tests/fields_tests/test_float_field.py
tests/fields_tests/test_foreign_key.py
tests/fields_tests/test_integer_field.py
dbeasyorm-0.0.0.dist-info/LICENSE
dbeasyorm-0.0.0.dist-info/METADATA
dbeasyorm-0.0.0.dist-info/WHEEL
dbeasyorm-0.0.0.dist-info/top_level.txt
dbeasyorm-0.0.0.dist-info/RECORD
