Metadata-Version: 2.1
Name: dbeasyorm
Version: 0.0.0
Summary: DBEasyORM is a lightweight and intuitive Object-Relational Mapping (ORM) library
Home-page: https://github.com/artur24814/DBEasyORM
Author: artur24814
Author-email: artur24814@gmail.com
License: MIT
Project-URL: Documentation, https://dbeasyorm.readthedocs.io
Project-URL: Source, https://github.com/artur24814/DBEasyORM
Project-URL: Bug Tracker, https://github.com/artur24814/DBEasyORM/issues
Classifier: Intended Audience :: Developers
Classifier: Topic :: Software Development :: Libraries :: Python Modules
Classifier: Topic :: Database
Classifier: Programming Language :: Python :: 3
Classifier: Programming Language :: Python :: 3.7
Classifier: Programming Language :: Python :: 3.8
Classifier: Programming Language :: Python :: 3.9
Classifier: Programming Language :: Python :: 3.10
Classifier: Programming Language :: Python :: 3.11
Classifier: License :: OSI Approved :: MIT License
Classifier: Operating System :: OS Independent
Requires-Python: >=3.8
License-File: LICENSE
Requires-Dist: colorama>=0.4.6
Provides-Extra: dev
Requires-Dist: pytest>=8.3.4; extra == "dev"
Requires-Dist: twine>=6.0.1; extra == "dev"
